{
  "file": "sample.log",
  "analyzed_at": "2025-08-08T00:20:32.871037",
  "total_lines": 10,
  "errors": 5,
  "warnings": 3,
  "top_errors": [
    [
      "ERROR Database connection failed: Connection timeout",
      3
    ],
    [
      "ERROR Failed to process request: Invalid JSON format",
      1
    ],
    [
      "ERROR Authentication failed for user admin",
      1
    ]
  ],
  "top_warnings": [
    [
      "WARNING High memory usage detected: 85%",
      1
    ],
    [
      "WARNING SSL certificate expires in 7 days",
      1
    ],
    [
      "WARNING High CPU usage: 92%",
      1
    ]
  ],
  "statistics": {
    "error_rate": 0.625,
    "warning_rate": 0.375,
    "errors_by_hour": {
      "10": 4,
      "11": 1
    },
    "warnings_by_hour": {
      "10": 2,
      "11": 1
    },
    "peak_error_hour": 10,
    "peak_warning_hour": 10
  },
  "error_details": [
    {
      "line_number": 3,
      "timestamp": "2024-08-08 10:35:22",
      "message": "2024-08-08 10:35:22 ERROR Database connection failed: Connection timeout",
      "extracted_error": "ERROR Database connection failed: Connection timeout"
    },
    {
      "line_number": 4,
      "timestamp": "2024-08-08 10:35:23",
      "message": "2024-08-08 10:35:23 ERROR Database connection failed: Connection timeout",
      "extracted_error": "ERROR Database connection failed: Connection timeout"
    },
    {
      "line_number": 6,
      "timestamp": "2024-08-08 10:45:33",
      "message": "2024-08-08 10:45:33 ERROR Failed to process request: Invalid JSON format",
      "extracted_error": "ERROR Failed to process request: Invalid JSON format"
    },
    {
      "line_number": 8,
      "timestamp": "2024-08-08 10:55:42",
      "message": "2024-08-08 10:55:42 ERROR Database connection failed: Connection timeout",
      "extracted_error": "ERROR Database connection failed: Connection timeout"
    },
    {
      "line_number": 10,
      "timestamp": "2024-08-08 11:05:55",
      "message": "2024-08-08 11:05:55 ERROR Authentication failed for user admin",
      "extracted_error": "ERROR Authentication failed for user admin"
    }
  ],
  "warning_details": [
    {
      "line_number": 2,
      "timestamp": "2024-08-08 10:30:20",
      "message": "2024-08-08 10:30:20 WARNING High memory usage detected: 85%",
      "extracted_warning": "WARNING High memory usage detected: 85%"
    },
    {
      "line_number": 5,
      "timestamp": "2024-08-08 10:40:11",
      "message": "2024-08-08 10:40:11 WARNING SSL certificate expires in 7 days",
      "extracted_warning": "WARNING SSL certificate expires in 7 days"
    },
    {
      "line_number": 9,
      "timestamp": "2024-08-08 11:00:18",
      "message": "2024-08-08 11:00:18 WARNING High CPU usage: 92%",
      "extracted_warning": "WARNING High CPU usage: 92%"
    }
  ]
}